README.md
setup.cfg
setup.py
dep_impact.egg-info/PKG-INFO
dep_impact.egg-info/SOURCES.txt
dep_impact.egg-info/dependency_links.txt
dep_impact.egg-info/requires.txt
dep_impact.egg-info/top_level.txt
depimpact/__init__.py
depimpact/conservative.py
depimpact/conversion.py
depimpact/correlation.py
depimpact/iterative_vines.py
depimpact/plots.py
depimpact/utils.py
depimpact/vinecopula.py