Metadata-Version: 1.0
Name: dep-impact
Version: 0.1
Summary: A Python package on the influence of dependencies in a structural reliability problem.
Home-page: https://github.com/NazBen/dep-impact
Author: Nazih Benoumechiara
Author-email: nazih.benoumechiara@gmail.com
License: MIT
Keywords: copula reliability regular-vines
Platform: UNKNOWN
